pyluks/__init__.py
pyluks/utilities.py
pyluks/vault_support.py
pyluks/fastluks/__init__.py
pyluks/fastluks/fastluks_lib.py
pyluks/fastluks/lockfile.py
pyluks/luksctl/__init__.py
pyluks/luksctl/luksctl_lib.py
pyluks/luksctl_api/__init__.py
pyluks/luksctl_api/app.py
pyluks/luksctl_api/gunicorn.conf.py
pyluks/luksctl_api/luksctl_api_master.py
pyluks/luksctl_api/luksctl_run.py
pyluks/luksctl_api/ssl_certificate.py
pyluks-0.0.2.data/scripts/fastluks
pyluks-0.0.2.data/scripts/luksctl
pyluks-0.0.2.data/scripts/luksctl_api
pyluks-0.0.2.dist-info/LICENSE
pyluks-0.0.2.dist-info/METADATA
pyluks-0.0.2.dist-info/WHEEL
pyluks-0.0.2.dist-info/top_level.txt
pyluks-0.0.2.dist-info/RECORD
