Metadata-Version: 2.1
Name: pyluks
Version: 0.0.2
Summary: Storage encryption through LUKS
Author-email: Daniele Colombo <daniele.colombo39@gmail.com>, Marco Antonio Tangaro <ma.tangaro@ibiom.cnr.it>
Project-URL: Homepage, https://github.com/Laniakea-elixir-it/pyluks
Project-URL: Issues, https://github.com/Laniakea-elixir-it/pyluks/issues
Classifier: Programming Language :: Python :: 3
Classifier: License :: OSI Approved :: MIT License
Requires-Python: >=3.6
License-File: LICENSE
Requires-Dist: zc.lockfile ==2.0
Requires-Dist: hvac ==0.11.2
Requires-Dist: distro ==1.3.0
Requires-Dist: flask ==2.0.0
Requires-Dist: gunicorn ==20.1.0
Requires-Dist: cryptography ==36.0.1
Requires-Dist: Werkzeug ==2.0.2
